AUTHORS.rst
CONTRIBUTING.rst
HISTORY.rst
LICENSE
MANIFEST.in
README.rst
setup.cfg
setup.py
docs/Makefile
docs/authors.rst
docs/conf.py
docs/contributing.rst
docs/history.rst
docs/index.rst
docs/installation.rst
docs/make.bat
docs/readme.rst
docs/usage.rst
examples/__init__.py
examples/send_text_example_prompt.py
tests/__init__.py
tests/test_zhimabot.py
zhimabot/__init__.py
zhimabot/zhimabot.py
zhimabot.egg-info/PKG-INFO
zhimabot.egg-info/SOURCES.txt
zhimabot.egg-info/dependency_links.txt
zhimabot.egg-info/entry_points.txt
zhimabot.egg-info/not-zip-safe
zhimabot.egg-info/requires.txt
zhimabot.egg-info/top_level.txt