Metadata-Version: 1.1
Name: zhimabot
Version: 0.1.0
Summary: Python library for zhimabot
Home-page: https://github.com/wwj718/zhimabot
Author: wenjiewu
Author-email: wuwenjie718@gmail.com
License: MIT license
Keywords: zhimabot
Platform: UNKNOWN
Classifier: Development Status :: 2 - Pre-Alpha
Classifier: Intended Audience :: Developers
Classifier: License :: OSI Approved :: MIT License
Classifier: Natural Language :: English
Classifier: Programming Language :: Python :: 2
Classifier: Programming Language :: Python :: 2.6
Classifier: Programming Language :: Python :: 2.7
Classifier: Programming Language :: Python :: 3
Classifier: Programming Language :: Python :: 3.3
Classifier: Programming Language :: Python :: 3.4
Classifier: Programming Language :: Python :: 3.5
